rdmaqe_test.py
rdmaqe/__about__.py
rdmaqe/__init__.py
rdmaqe/rdmaqe_test.py
rdmaqe/common/__init__.py
rdmaqe/common/cli.py
rdmaqe/common/file_libs.py
rdmaqe/common/fmf_tools.py
rdmaqe/common/tc.py
rdmaqe/rdma/__init__.py
rdmaqe/rdma/general.py
rdmaqe/rdma/opa.py
rdmaqe/rdma/roce.py
rdmaqe/rdma/rxe.py
rdmaqe/rdma/siw.py
rdmaqe/rdma/sriov.py
rdmaqe/rdma/sriov/__init__.py
rdmaqe/rdma/sriov/abc_sriov.py
rdmaqe/rdma/sriov/sriov.py
python_rdma_qe-0.0.8.dist-info/METADATA
python_rdma_qe-0.0.8.dist-info/WHEEL
python_rdma_qe-0.0.8.dist-info/licenses/LICENSE
python_rdma_qe-0.0.8.dist-info/RECORD
